setup.py
distributions_101/Binomialdistribution.py
distributions_101/Gaussiandistribution.py
distributions_101/Generaldistribution.py
distributions_101/__init__.py
distributions_101.egg-info/PKG-INFO
distributions_101.egg-info/SOURCES.txt
distributions_101.egg-info/dependency_links.txt
distributions_101.egg-info/not-zip-safe
distributions_101.egg-info/top_level.txt